{
  "hash": "2f1a821020d19760d280516832b2df6a",
  "result": {
    "markdown": "---\ntitle: \"Structure\"\nformat: html\n---\n\n\nTibbles are formatted like a __data.frame__ but have some extra functions and terminology.\n\nFor demostration we'll load and subset the `hbr_maples` data from the [lterdatasampler package](/datasets/lterdatasampler.qmd) (hyperlink includes install instructions) and view it.\n\n\n::: {.cell}\n\n```{.r .cell-code}\n#Load package\nlibrary(\"lterdatasampler\")\n#Subset of hbr_maples tibble\ntibble::as_tibble(lterdatasampler::hbr_maples)[1:10,1:7]\n```\n\n::: {.cell-output .cell-output-stdout}\n```\n# A tibble: 10 × 7\n    year watershed elevation transect sample stem_length leaf1area\n   <dbl> <fct>     <fct>     <fct>    <fct>        <dbl>     <dbl>\n 1  2003 Reference Low       R1       1             86.9     13.8 \n 2  2003 Reference Low       R1       2            114       14.6 \n 3  2003 Reference Low       R1       3             83.5     12.5 \n 4  2003 Reference Low       R1       4             68.1      9.97\n 5  2003 Reference Low       R1       5             72.1      6.84\n 6  2003 Reference Low       R1       6             77.7      9.66\n 7  2003 Reference Low       R1       7             85.5      8.82\n 8  2003 Reference Low       R1       8             81.6      5.83\n 9  2003 Reference Low       R1       9             92.9      8.11\n10  2003 Reference Low       R1       10            59.6      3.02\n```\n:::\n:::\n\n\nLet's go over some of its components:\n\n- Size info\n- Variables/columns\n- observations/rows\n\n## Size info\n\nAt the top of the __tibble__ it tells us the size.\nThe first number is the rows and the second is the columns.\n\nIn the above example we have:\n\n- 10 rows/observations\n- 7 columns/variables\n\n## Rows/observations\n\nAs in a __data.frame__ each observation is within its own row.\nThe contents of an observation/row is determined by your dataset and how you want to analyse or visualise it.\nThere are many ways to manipulate __tibbles__ with the [dplyr](/dplyr/dplyr.qmd), [tidyr](/tidyr/tidyr.qmd), and other tidyverse packages. \n\n__Tibble__ rows do not have row names and you cannot/should not give them row names.\nThey are numbered/indexxed instead.\n\n## Variables/columns\n\nA __tibble__ will have a certain number of columns.\n\nEach column has a name that is at the top. \nFor example:\n\n- year\n- watershed\n- elevation\n\nBelow the column/variable names is the data class/type of the column.\nAll the entries within a single column will have the same data class.\nThese include:\n\n- __\\<int>__: [Integer](https://neof-workshops.github.io/R_j4c0xh/04-R_objects.html#numeric)\n- __\\<dbl>__: [Double](https://neof-workshops.github.io/R_j4c0xh/04-R_objects.html#numeric)\n- __\\<chr>__: [Character/String](https://neof-workshops.github.io/R_j4c0xh/04-R_objects.html#string)\n- __\\<fct>__: [Factor](https://neof-workshops.github.io/R_j4c0xh/04-R_objects.html#string)\n- __\\<lgl>__: [Logical](https://neof-workshops.github.io/R_j4c0xh/04-R_objects.html#string)\n- __\\<date>__: Date (MG ADD LINK TO INFO ABOUT DATE CLASS, MOST LIKELY IN LUBRIDATE SECTION)\n- __\\<list>__: List\n\nBelow is an example of a __tibble__ with a column for each of these classes.\n\n\n::: {.cell}\n::: {.cell-output .cell-output-stdout}\n```\n# A tibble: 4 × 7\n  Integers   Doubles Characters Factors Logicals Dates      Lists    \n     <int>     <dbl> <chr>      <fct>   <lgl>    <date>     <list>   \n1      101     0.345 One        A       TRUE     0001-01-20 <dbl [3]>\n2       21     3.14  sentence   B       TRUE     0002-01-20 <dbl [3]>\n3        3    78.9   is         B       FALSE    0003-01-20 <dbl [3]>\n4        0 20001.    enough     A       FALSE    0004-01-20 <dbl [3]>\n```\n:::\n:::\n\n\nAbove you can see that when you view a __tibble__, by printing it or viewing it in an Rstudio tab, it will align the values in the columns in a easy to read manner.\nThis is especially useful for numeric (integers & doubles) columns where the numbers are aligned by place value.\nThis allows you to easily compare the size of numbers in the same column.",
    "supporting": [],
    "filters": [
      "rmarkdown/pagebreak.lua"
    ],
    "includes": {},
    "engineDependencies": {},
    "preserve": {},
    "postProcess": true
  }
}